octid/__init__.py
octid/octid.py
octid-1.1.6.dist-info/LICENSE
octid-1.1.6.dist-info/METADATA
octid-1.1.6.dist-info/WHEEL
octid-1.1.6.dist-info/top_level.txt
octid-1.1.6.dist-info/RECORD
