Metadata-Version: 2.1
Name: octid
Version: 1.1.6
Summary: One-Class learning-based tool for Tumor Image Detection
Home-page: UNKNOWN
Author: Litao Yang, Yanan Wang
Author-email: litao.yang@monash.edu, yanan.wang1@monash.edu
License: UNKNOWN
Platform: any
Classifier: Programming Language :: Python :: 3
Classifier: License :: OSI Approved :: MIT License
Classifier: Environment :: GPU :: NVIDIA CUDA
Requires-Python: >=3.6
Requires-Dist: torch
Requires-Dist: torchvision
Requires-Dist: matplotlib
Requires-Dist: numpy
Requires-Dist: sklearn
Requires-Dist: pandas
Requires-Dist: umap-learn
